pt13-3.13.0.dev4.dist-info/METADATA
pt13-3.13.0.dev4.dist-info/WHEEL
pt13-3.13.0.dev4.dist-info/entry_points.txt
pt13-3.13.0.dev4.dist-info/licenses/LICENSE
pt13/__init__.py
pt13/app.py
pt13/thirteen/__init__.py
pt13/thirteen/more_iters/__init__.py
pt13/thirteen/more_iters/buckets.py
pt13/thirteen/stdlib_changes_p13/__init__.py
pt13/thirteen/stdlib_changes_p13/math_changes.py
pt13/thirteen/stdlib_changes_p13/path_changes.py
pt13/thirteen/stdlib_changes_p13/typing_changes.py
pt13-3.13.0.dev4.dist-info/RECORD
