Metadata-Version: 2.1
Name: pt13
Version: 3.13.0.dev4
Summary: Stuff for Python 3.13.0
Author-Email: "D. Alex Graham" <alex@aode.space>
License: MIT
Requires-Python: >=3.13
Requires-Dist: typer>=0.12.5
Requires-Dist: version3900==3.9.0a0
